<?xml version="1.0" encoding="utf-8"?>
<ArrayOfAssignment xmlns:xsi="http://www.w3.org/2001/XMLSchema-instance" xmlns:xsd="http://www.w3.org/2001/XMLSchema">
  <Assignment>
    <Id>72</Id>
    <CallId>1</CallId>
    <VolunteerId>308354748</VolunteerId>
    <AppointmentTime>2025-02-04T21:08:28</AppointmentTime>
    <FinishAppointmentTime>2025-02-04T20:08:28</FinishAppointmentTime>
    <FinishAppointmentType>CancellationHasExpired</FinishAppointmentType>
  </Assignment>
  <Assignment>
    <Id>73</Id>
    <CallId>2</CallId>
    <VolunteerId>308354748</VolunteerId>
    <AppointmentTime>2025-02-05T12:28:15</AppointmentTime>
    <FinishAppointmentTime>2025-02-05T17:28:15</FinishAppointmentTime>
    <FinishAppointmentType>CancellationHasExpired</FinishAppointmentType>
  </Assignment>
  <Assignment>
    <Id>74</Id>
    <CallId>3</CallId>
    <VolunteerId>308354748</VolunteerId>
    <AppointmentTime>2025-01-26T03:57:48</AppointmentTime>
    <FinishAppointmentTime>2025-01-25T06:57:48</FinishAppointmentTime>
    <FinishAppointmentType>CancellationHasExpired</FinishAppointmentType>
  </Assignment>
  <Assignment>
    <Id>76</Id>
    <CallId>4</CallId>
    <VolunteerId>365589497</VolunteerId>
    <AppointmentTime>2025-02-07T01:49:21</AppointmentTime>
    <FinishAppointmentTime>2025-02-06T17:49:21</FinishAppointmentTime>
    <FinishAppointmentType>CancellationHasExpired</FinishAppointmentType>
  </Assignment>
  <Assignment>
    <Id>77</Id>
    <CallId>5</CallId>
    <VolunteerId>365589497</VolunteerId>
    <AppointmentTime>2025-02-08T00:25:26</AppointmentTime>
    <FinishAppointmentTime>2025-02-07T06:25:26</FinishAppointmentTime>
    <FinishAppointmentType>CancellationHasExpired</FinishAppointmentType>
  </Assignment>
  <Assignment>
    <Id>78</Id>
    <CallId>6</CallId>
    <VolunteerId>365589497</VolunteerId>
    <AppointmentTime>2025-02-01T02:00:31</AppointmentTime>
    <FinishAppointmentTime>2025-01-31T20:00:31</FinishAppointmentTime>
    <FinishAppointmentType>CancellationHasExpired</FinishAppointmentType>
  </Assignment>
  <Assignment>
    <Id>80</Id>
    <CallId>7</CallId>
    <VolunteerId>105437713</VolunteerId>
    <AppointmentTime>2025-01-31T14:12:29</AppointmentTime>
    <FinishAppointmentTime>2025-01-31T07:12:29</FinishAppointmentTime>
    <FinishAppointmentType>CancellationHasExpired</FinishAppointmentType>
  </Assignment>
  <Assignment>
    <Id>81</Id>
    <CallId>9</CallId>
    <VolunteerId>105437713</VolunteerId>
    <AppointmentTime>2025-02-07T11:35:39</AppointmentTime>
    <FinishAppointmentTime>2025-02-06T21:35:39</FinishAppointmentTime>
    <FinishAppointmentType>CancellationHasExpired</FinishAppointmentType>
  </Assignment>
  <Assignment>
    <Id>82</Id>
    <CallId>10</CallId>
    <VolunteerId>105437713</VolunteerId>
    <AppointmentTime>2025-01-31T14:32:23</AppointmentTime>
    <FinishAppointmentTime>2025-01-31T07:32:23</FinishAppointmentTime>
    <FinishAppointmentType>CancellationHasExpired</FinishAppointmentType>
  </Assignment>
  <Assignment>
    <Id>84</Id>
    <CallId>11</CallId>
    <VolunteerId>818642626</VolunteerId>
    <AppointmentTime>2025-02-05T08:25:03</AppointmentTime>
    <FinishAppointmentTime>2025-02-05T09:25:03</FinishAppointmentTime>
    <FinishAppointmentType>CancellationHasExpired</FinishAppointmentType>
  </Assignment>
  <Assignment>
    <Id>85</Id>
    <CallId>12</CallId>
    <VolunteerId>818642626</VolunteerId>
    <AppointmentTime>2025-02-07T12:42:52</AppointmentTime>
    <FinishAppointmentTime>2025-02-06T17:42:52</FinishAppointmentTime>
    <FinishAppointmentType>CancellationHasExpired</FinishAppointmentType>
  </Assignment>
  <Assignment>
    <Id>86</Id>
    <CallId>14</CallId>
    <VolunteerId>818642626</VolunteerId>
    <AppointmentTime>2025-02-05T21:48:07</AppointmentTime>
    <FinishAppointmentTime>2025-02-06T01:48:07</FinishAppointmentTime>
    <FinishAppointmentType>CancellationHasExpired</FinishAppointmentType>
  </Assignment>
  <Assignment>
    <Id>88</Id>
    <CallId>15</CallId>
    <VolunteerId>749491908</VolunteerId>
    <AppointmentTime>2025-01-31T14:30:52</AppointmentTime>
    <FinishAppointmentTime>2025-01-31T21:30:52</FinishAppointmentTime>
    <FinishAppointmentType>CancellationHasExpired</FinishAppointmentType>
  </Assignment>
  <Assignment>
    <Id>89</Id>
    <CallId>17</CallId>
    <VolunteerId>749491908</VolunteerId>
    <AppointmentTime>2025-01-27T11:44:30</AppointmentTime>
    <FinishAppointmentTime>2025-01-28T02:44:30</FinishAppointmentTime>
    <FinishAppointmentType>CancellationHasExpired</FinishAppointmentType>
  </Assignment>
  <Assignment>
    <Id>90</Id>
    <CallId>18</CallId>
    <VolunteerId>749491908</VolunteerId>
    <AppointmentTime>2025-01-29T23:52:42</AppointmentTime>
    <FinishAppointmentTime>2025-01-29T06:52:42</FinishAppointmentTime>
    <FinishAppointmentType>CancellationHasExpired</FinishAppointmentType>
  </Assignment>
  <Assignment>
    <Id>91</Id>
    <CallId>19</CallId>
    <VolunteerId>386632668</VolunteerId>
    <AppointmentTime>2025-02-06T23:46:51</AppointmentTime>
    <FinishAppointmentTime>2025-02-06T20:46:51</FinishAppointmentTime>
    <FinishAppointmentType>CancellationHasExpired</FinishAppointmentType>
  </Assignment>
  <Assignment>
    <Id>92</Id>
    <CallId>21</CallId>
    <VolunteerId>293479554</VolunteerId>
    <AppointmentTime>2025-02-03T01:06:21</AppointmentTime>
    <FinishAppointmentTime>2025-02-02T09:06:21</FinishAppointmentTime>
    <FinishAppointmentType>CancellationHasExpired</FinishAppointmentType>
  </Assignment>
  <Assignment>
    <Id>93</Id>
    <CallId>22</CallId>
    <VolunteerId>640478687</VolunteerId>
    <AppointmentTime>2025-02-07T03:37:08</AppointmentTime>
    <FinishAppointmentTime>2025-02-07T05:37:08</FinishAppointmentTime>
    <FinishAppointmentType>CancellationHasExpired</FinishAppointmentType>
  </Assignment>
  <Assignment>
    <Id>94</Id>
    <CallId>23</CallId>
    <VolunteerId>609574512</VolunteerId>
    <AppointmentTime>2025-01-31T08:43:55</AppointmentTime>
    <FinishAppointmentTime>2025-01-31T13:43:55</FinishAppointmentTime>
    <FinishAppointmentType>CancellationHasExpired</FinishAppointmentType>
  </Assignment>
  <Assignment>
    <Id>95</Id>
    <CallId>25</CallId>
    <VolunteerId>703398991</VolunteerId>
    <AppointmentTime>2025-02-07T17:40:33</AppointmentTime>
    <FinishAppointmentTime>2025-02-07T11:40:33</FinishAppointmentTime>
    <FinishAppointmentType>WasTreated</FinishAppointmentType>
  </Assignment>
  <Assignment>
    <Id>96</Id>
    <CallId>26</CallId>
    <VolunteerId>292760939</VolunteerId>
    <AppointmentTime>2025-02-02T03:51:32</AppointmentTime>
    <FinishAppointmentTime>2025-02-02T01:51:32</FinishAppointmentTime>
    <FinishAppointmentType>CancellationHasExpired</FinishAppointmentType>
  </Assignment>
  <Assignment>
    <Id>97</Id>
    <CallId>27</CallId>
    <VolunteerId>847099089</VolunteerId>
    <AppointmentTime>2025-02-07T03:51:12</AppointmentTime>
    <FinishAppointmentTime>2025-02-07T12:51:12</FinishAppointmentTime>
    <FinishAppointmentType>WasTreated</FinishAppointmentType>
  </Assignment>
  <Assignment>
    <Id>98</Id>
    <CallId>28</CallId>
    <VolunteerId>192075903</VolunteerId>
    <AppointmentTime>2025-02-07T17:13:44</AppointmentTime>
    <FinishAppointmentTime>2025-02-07T01:13:44</FinishAppointmentTime>
    <FinishAppointmentType>CancellationHasExpired</FinishAppointmentType>
  </Assignment>
  <Assignment>
    <Id>99</Id>
    <CallId>32</CallId>
    <VolunteerId>0</VolunteerId>
    <AppointmentTime>2025-02-07T06:49:31</AppointmentTime>
    <FinishAppointmentTime>2025-02-07T06:49:31</FinishAppointmentTime>
    <FinishAppointmentType>CancellationHasExpired</FinishAppointmentType>
  </Assignment>
  <Assignment>
    <Id>100</Id>
    <CallId>33</CallId>
    <VolunteerId>0</VolunteerId>
    <AppointmentTime>2025-02-07T06:49:31</AppointmentTime>
    <FinishAppointmentTime>2025-02-07T06:49:31</FinishAppointmentTime>
    <FinishAppointmentType>CancellationHasExpired</FinishAppointmentType>
  </Assignment>
  <Assignment>
    <Id>101</Id>
    <CallId>34</CallId>
    <VolunteerId>0</VolunteerId>
    <AppointmentTime>2025-02-07T06:49:31</AppointmentTime>
    <FinishAppointmentTime>2025-02-07T06:49:31</FinishAppointmentTime>
    <FinishAppointmentType>CancellationHasExpired</FinishAppointmentType>
  </Assignment>
  <Assignment>
    <Id>102</Id>
    <CallId>35</CallId>
    <VolunteerId>0</VolunteerId>
    <AppointmentTime>2025-02-07T06:49:31</AppointmentTime>
    <FinishAppointmentTime>2025-02-07T06:49:31</FinishAppointmentTime>
    <FinishAppointmentType>CancellationHasExpired</FinishAppointmentType>
  </Assignment>
  <Assignment>
    <Id>103</Id>
    <CallId>37</CallId>
    <VolunteerId>0</VolunteerId>
    <AppointmentTime>2025-02-07T06:49:31</AppointmentTime>
    <FinishAppointmentTime>2025-02-07T06:49:31</FinishAppointmentTime>
    <FinishAppointmentType>CancellationHasExpired</FinishAppointmentType>
  </Assignment>
  <Assignment>
    <Id>105</Id>
    <CallId>39</CallId>
    <VolunteerId>0</VolunteerId>
    <AppointmentTime>2025-02-07T06:59:31</AppointmentTime>
    <FinishAppointmentTime>2025-02-07T06:59:31</FinishAppointmentTime>
    <FinishAppointmentType>CancellationHasExpired</FinishAppointmentType>
  </Assignment>
  <Assignment>
    <Id>106</Id>
    <CallId>40</CallId>
    <VolunteerId>0</VolunteerId>
    <AppointmentTime>2025-02-07T06:59:31</AppointmentTime>
    <FinishAppointmentTime>2025-02-07T06:59:31</FinishAppointmentTime>
    <FinishAppointmentType>CancellationHasExpired</FinishAppointmentType>
  </Assignment>
  <Assignment>
    <Id>108</Id>
    <CallId>41</CallId>
    <VolunteerId>0</VolunteerId>
    <AppointmentTime>2025-02-07T06:59:31</AppointmentTime>
    <FinishAppointmentTime>2025-02-07T06:59:31</FinishAppointmentTime>
    <FinishAppointmentType>CancellationHasExpired</FinishAppointmentType>
  </Assignment>
  <Assignment>
    <Id>109</Id>
    <CallId>42</CallId>
    <VolunteerId>0</VolunteerId>
    <AppointmentTime>2025-02-07T06:59:31</AppointmentTime>
    <FinishAppointmentTime>2025-02-07T06:59:31</FinishAppointmentTime>
    <FinishAppointmentType>CancellationHasExpired</FinishAppointmentType>
  </Assignment>
  <Assignment>
    <Id>110</Id>
    <CallId>43</CallId>
    <VolunteerId>0</VolunteerId>
    <AppointmentTime>2025-02-07T06:59:31</AppointmentTime>
    <FinishAppointmentTime>2025-02-07T06:59:31</FinishAppointmentTime>
    <FinishAppointmentType>CancellationHasExpired</FinishAppointmentType>
  </Assignment>
  <Assignment>
    <Id>111</Id>
    <CallId>44</CallId>
    <VolunteerId>0</VolunteerId>
    <AppointmentTime>2025-02-07T06:59:31</AppointmentTime>
    <FinishAppointmentTime>2025-02-07T06:59:31</FinishAppointmentTime>
    <FinishAppointmentType>CancellationHasExpired</FinishAppointmentType>
  </Assignment>
  <Assignment>
    <Id>112</Id>
    <CallId>45</CallId>
    <VolunteerId>0</VolunteerId>
    <AppointmentTime>2025-02-07T06:59:31</AppointmentTime>
    <FinishAppointmentTime>2025-02-07T06:59:31</FinishAppointmentTime>
    <FinishAppointmentType>CancellationHasExpired</FinishAppointmentType>
  </Assignment>
  <Assignment>
    <Id>113</Id>
    <CallId>46</CallId>
    <VolunteerId>0</VolunteerId>
    <AppointmentTime>2025-02-07T06:59:31</AppointmentTime>
    <FinishAppointmentTime>2025-02-07T06:59:31</FinishAppointmentTime>
    <FinishAppointmentType>CancellationHasExpired</FinishAppointmentType>
  </Assignment>
  <Assignment>
    <Id>114</Id>
    <CallId>47</CallId>
    <VolunteerId>0</VolunteerId>
    <AppointmentTime>2025-02-07T06:59:31</AppointmentTime>
    <FinishAppointmentTime>2025-02-07T06:59:31</FinishAppointmentTime>
    <FinishAppointmentType>CancellationHasExpired</FinishAppointmentType>
  </Assignment>
  <Assignment>
    <Id>115</Id>
    <CallId>48</CallId>
    <VolunteerId>0</VolunteerId>
    <AppointmentTime>2025-02-07T06:59:31</AppointmentTime>
    <FinishAppointmentTime>2025-02-07T06:59:31</FinishAppointmentTime>
    <FinishAppointmentType>CancellationHasExpired</FinishAppointmentType>
  </Assignment>
  <Assignment>
    <Id>116</Id>
    <CallId>49</CallId>
    <VolunteerId>0</VolunteerId>
    <AppointmentTime>2025-02-07T06:59:31</AppointmentTime>
    <FinishAppointmentTime>2025-02-07T06:59:31</FinishAppointmentTime>
    <FinishAppointmentType>CancellationHasExpired</FinishAppointmentType>
  </Assignment>
  <Assignment>
    <Id>117</Id>
    <CallId>50</CallId>
    <VolunteerId>0</VolunteerId>
    <AppointmentTime>2025-02-07T06:59:31</AppointmentTime>
    <FinishAppointmentTime>2025-02-07T06:59:31</FinishAppointmentTime>
    <FinishAppointmentType>CancellationHasExpired</FinishAppointmentType>
  </Assignment>
  <Assignment>
    <Id>118</Id>
    <CallId>51</CallId>
    <VolunteerId>0</VolunteerId>
    <AppointmentTime>2025-02-07T06:59:31</AppointmentTime>
    <FinishAppointmentTime>2025-02-07T06:59:31</FinishAppointmentTime>
    <FinishAppointmentType>CancellationHasExpired</FinishAppointmentType>
  </Assignment>
  <Assignment>
    <Id>119</Id>
    <CallId>52</CallId>
    <VolunteerId>0</VolunteerId>
    <AppointmentTime>2025-02-07T06:59:31</AppointmentTime>
    <FinishAppointmentTime>2025-02-07T06:59:31</FinishAppointmentTime>
    <FinishAppointmentType>CancellationHasExpired</FinishAppointmentType>
  </Assignment>
  <Assignment>
    <Id>120</Id>
    <CallId>53</CallId>
    <VolunteerId>0</VolunteerId>
    <AppointmentTime>2025-02-07T06:59:31</AppointmentTime>
    <FinishAppointmentTime>2025-02-07T06:59:31</FinishAppointmentTime>
    <FinishAppointmentType>CancellationHasExpired</FinishAppointmentType>
  </Assignment>
  <Assignment>
    <Id>121</Id>
    <CallId>55</CallId>
    <VolunteerId>0</VolunteerId>
    <AppointmentTime>2025-02-07T06:59:31</AppointmentTime>
    <FinishAppointmentTime>2025-02-07T06:59:31</FinishAppointmentTime>
    <FinishAppointmentType>CancellationHasExpired</FinishAppointmentType>
  </Assignment>
  <Assignment>
    <Id>122</Id>
    <CallId>57</CallId>
    <VolunteerId>0</VolunteerId>
    <AppointmentTime>2025-02-07T06:59:31</AppointmentTime>
    <FinishAppointmentTime>2025-02-07T06:59:31</FinishAppointmentTime>
    <FinishAppointmentType>CancellationHasExpired</FinishAppointmentType>
  </Assignment>
  <Assignment>
    <Id>123</Id>
    <CallId>59</CallId>
    <VolunteerId>0</VolunteerId>
    <AppointmentTime>2025-02-07T06:59:31</AppointmentTime>
    <FinishAppointmentTime>2025-02-07T06:59:31</FinishAppointmentTime>
    <FinishAppointmentType>CancellationHasExpired</FinishAppointmentType>
  </Assignment>
  <Assignment>
    <Id>124</Id>
    <CallId>60</CallId>
    <VolunteerId>0</VolunteerId>
    <AppointmentTime>2025-02-07T06:59:31</AppointmentTime>
    <FinishAppointmentTime>2025-02-07T06:59:31</FinishAppointmentTime>
    <FinishAppointmentType>CancellationHasExpired</FinishAppointmentType>
  </Assignment>
  <Assignment>
    <Id>125</Id>
    <CallId>62</CallId>
    <VolunteerId>0</VolunteerId>
    <AppointmentTime>2025-02-07T06:59:31</AppointmentTime>
    <FinishAppointmentTime>2025-02-07T06:59:31</FinishAppointmentTime>
    <FinishAppointmentType>CancellationHasExpired</FinishAppointmentType>
  </Assignment>
  <Assignment>
    <Id>126</Id>
    <CallId>63</CallId>
    <VolunteerId>0</VolunteerId>
    <AppointmentTime>2025-02-07T06:59:31</AppointmentTime>
    <FinishAppointmentTime>2025-02-07T06:59:31</FinishAppointmentTime>
    <FinishAppointmentType>CancellationHasExpired</FinishAppointmentType>
  </Assignment>
  <Assignment>
    <Id>127</Id>
    <CallId>64</CallId>
    <VolunteerId>0</VolunteerId>
    <AppointmentTime>2025-02-07T06:59:31</AppointmentTime>
    <FinishAppointmentTime>2025-02-07T06:59:31</FinishAppointmentTime>
    <FinishAppointmentType>CancellationHasExpired</FinishAppointmentType>
  </Assignment>
  <Assignment>
    <Id>128</Id>
    <CallId>65</CallId>
    <VolunteerId>0</VolunteerId>
    <AppointmentTime>2025-02-07T06:59:31</AppointmentTime>
    <FinishAppointmentTime>2025-02-07T06:59:31</FinishAppointmentTime>
    <FinishAppointmentType>CancellationHasExpired</FinishAppointmentType>
  </Assignment>
  <Assignment>
    <Id>129</Id>
    <CallId>67</CallId>
    <VolunteerId>0</VolunteerId>
    <AppointmentTime>2025-02-07T06:59:31</AppointmentTime>
    <FinishAppointmentTime>2025-02-07T06:59:31</FinishAppointmentTime>
    <FinishAppointmentType>CancellationHasExpired</FinishAppointmentType>
  </Assignment>
  <Assignment>
    <Id>130</Id>
    <CallId>68</CallId>
    <VolunteerId>0</VolunteerId>
    <AppointmentTime>2025-02-07T06:59:31</AppointmentTime>
    <FinishAppointmentTime>2025-02-07T06:59:31</FinishAppointmentTime>
    <FinishAppointmentType>CancellationHasExpired</FinishAppointmentType>
  </Assignment>
  <Assignment>
    <Id>131</Id>
    <CallId>69</CallId>
    <VolunteerId>0</VolunteerId>
    <AppointmentTime>2025-02-07T06:59:31</AppointmentTime>
    <FinishAppointmentTime>2025-02-07T06:59:31</FinishAppointmentTime>
    <FinishAppointmentType>CancellationHasExpired</FinishAppointmentType>
  </Assignment>
  <Assignment>
    <Id>132</Id>
    <CallId>70</CallId>
    <VolunteerId>0</VolunteerId>
    <AppointmentTime>2025-02-07T06:59:31</AppointmentTime>
    <FinishAppointmentTime>2025-02-07T06:59:31</FinishAppointmentTime>
    <FinishAppointmentType>CancellationHasExpired</FinishAppointmentType>
  </Assignment>
  <Assignment>
    <Id>104</Id>
    <CallId>38</CallId>
    <VolunteerId>386632668</VolunteerId>
    <AppointmentTime>2025-02-07T06:40:03.5258646+02:00</AppointmentTime>
    <FinishAppointmentTime>2025-02-07T06:59:31</FinishAppointmentTime>
    <FinishAppointmentType>CancellationHasExpired</FinishAppointmentType>
  </Assignment>
  <Assignment>
    <Id>107</Id>
    <CallId>61</CallId>
    <VolunteerId>847099089</VolunteerId>
    <AppointmentTime>2025-02-07T06:40:03.7327354+02:00</AppointmentTime>
    <FinishAppointmentTime>2025-02-07T06:59:31</FinishAppointmentTime>
    <FinishAppointmentType>CancellationHasExpired</FinishAppointmentType>
  </Assignment>
  <Assignment>
    <Id>133</Id>
    <CallId>36</CallId>
    <VolunteerId>259000414</VolunteerId>
    <AppointmentTime>2025-02-07T06:40:04.6757232+02:00</AppointmentTime>
    <FinishAppointmentTime xsi:nil="true" />
    <FinishAppointmentType xsi:nil="true" />
  </Assignment>
  <Assignment>
    <Id>136</Id>
    <CallId>54</CallId>
    <VolunteerId>703398991</VolunteerId>
    <AppointmentTime>2025-02-07T06:40:05.9545116+02:00</AppointmentTime>
    <FinishAppointmentTime>2025-02-07T07:49:31</FinishAppointmentTime>
    <FinishAppointmentType>CancellationHasExpired</FinishAppointmentType>
  </Assignment>
  <Assignment>
    <Id>71</Id>
    <CallId>8</CallId>
    <VolunteerId>308354748</VolunteerId>
    <AppointmentTime>2025-02-07T22:46:25</AppointmentTime>
    <FinishAppointmentTime>2025-02-07T08:49:31</FinishAppointmentTime>
    <FinishAppointmentType>CancellationHasExpired</FinishAppointmentType>
  </Assignment>
  <Assignment>
    <Id>87</Id>
    <CallId>24</CallId>
    <VolunteerId>749491908</VolunteerId>
    <AppointmentTime>2025-02-07T18:22:04</AppointmentTime>
    <FinishAppointmentTime>2025-02-07T09:29:31</FinishAppointmentTime>
    <FinishAppointmentType>CancellationHasExpired</FinishAppointmentType>
  </Assignment>
  <Assignment>
    <Id>138</Id>
    <CallId>31</CallId>
    <VolunteerId>386632668</VolunteerId>
    <AppointmentTime>2025-02-07T06:40:06.7404824+02:00</AppointmentTime>
    <FinishAppointmentTime>2025-02-07T10:39:31</FinishAppointmentTime>
    <FinishAppointmentType>CancellationHasExpired</FinishAppointmentType>
  </Assignment>
  <Assignment>
    <Id>139</Id>
    <CallId>29</CallId>
    <VolunteerId>847099089</VolunteerId>
    <AppointmentTime>2025-02-07T06:40:06.9950273+02:00</AppointmentTime>
    <FinishAppointmentTime>2025-02-07T12:53:31</FinishAppointmentTime>
    <FinishAppointmentType>CancellationHasExpired</FinishAppointmentType>
  </Assignment>
  <Assignment>
    <Id>140</Id>
    <CallId>66</CallId>
    <VolunteerId>703398991</VolunteerId>
    <AppointmentTime>2025-02-07T06:40:08.7366358+02:00</AppointmentTime>
    <FinishAppointmentTime>2025-02-07T15:17:31</FinishAppointmentTime>
    <FinishAppointmentType>CancellationHasExpired</FinishAppointmentType>
  </Assignment>
  <Assignment>
    <Id>137</Id>
    <CallId>30</CallId>
    <VolunteerId>192075903</VolunteerId>
    <AppointmentTime>2025-02-07T06:40:06.1045522+02:00</AppointmentTime>
    <FinishAppointmentTime>2025-02-07T15:57:31</FinishAppointmentTime>
    <FinishAppointmentType>CancellationHasExpired</FinishAppointmentType>
  </Assignment>
  <Assignment>
    <Id>75</Id>
    <CallId>13</CallId>
    <VolunteerId>365589497</VolunteerId>
    <AppointmentTime>2025-02-06T23:07:59</AppointmentTime>
    <FinishAppointmentTime>2025-02-07T17:09:31</FinishAppointmentTime>
    <FinishAppointmentType>CancellationHasExpired</FinishAppointmentType>
  </Assignment>
  <Assignment>
    <Id>134</Id>
    <CallId>58</CallId>
    <VolunteerId>292760939</VolunteerId>
    <AppointmentTime>2025-02-07T06:40:04.8869158+02:00</AppointmentTime>
    <FinishAppointmentTime>2025-02-07T17:37:31</FinishAppointmentTime>
    <FinishAppointmentType>CancellationHasExpired</FinishAppointmentType>
  </Assignment>
  <Assignment>
    <Id>135</Id>
    <CallId>56</CallId>
    <VolunteerId>853422373</VolunteerId>
    <AppointmentTime>2025-02-07T06:40:05.7388403+02:00</AppointmentTime>
    <FinishAppointmentTime>2025-02-07T17:45:31</FinishAppointmentTime>
    <FinishAppointmentType>CancellationHasExpired</FinishAppointmentType>
  </Assignment>
  <Assignment>
    <Id>83</Id>
    <CallId>20</CallId>
    <VolunteerId>818642626</VolunteerId>
    <AppointmentTime>2025-02-07T16:56:32</AppointmentTime>
    <FinishAppointmentTime>2025-02-07T22:57:31</FinishAppointmentTime>
    <FinishAppointmentType>CancellationHasExpired</FinishAppointmentType>
  </Assignment>
  <Assignment>
    <Id>79</Id>
    <CallId>16</CallId>
    <VolunteerId>105437713</VolunteerId>
    <AppointmentTime>2025-02-08T00:41:40</AppointmentTime>
    <FinishAppointmentTime>2025-02-08T01:49:31</FinishAppointmentTime>
    <FinishAppointmentType>CancellationHasExpired</FinishAppointmentType>
  </Assignment>
</ArrayOfAssignment>